<NAMEFILES>
  <NAMEFILE FILENAME="ENG1996.csv" COUNTRY="ENGLAND" YEAR="1996"/>
  <NAMEFILE FILENAME="ENG1997.csv" COUNTRY="ENGLAND" YEAR="1997"/>
  <NAMEFILE FILENAME="ENG1998.csv" COUNTRY="ENGLAND" YEAR="1998"/>
  <NAMEFILE FILENAME="ENG1999.csv" COUNTRY="ENGLAND" YEAR="1999"/>
  <NAMEFILE FILENAME="ENG2000.csv" COUNTRY="ENGLAND" YEAR="2000"/>
  <NAMEFILE FILENAME="ENG2001.csv" COUNTRY="ENGLAND" YEAR="2001"/>
  <NAMEFILE FILENAME="ENG2002.csv" COUNTRY="ENGLAND" YEAR="2002"/>
  <NAMEFILE FILENAME="ENG2003.csv" COUNTRY="ENGLAND" YEAR="2003"/>
  <NAMEFILE FILENAME="ENG2004.csv" COUNTRY="ENGLAND" YEAR="2004"/>
  <NAMEFILE FILENAME="ENG2005.csv" COUNTRY="ENGLAND" YEAR="2005"/>
  <NAMEFILE FILENAME="ENG2006.csv" COUNTRY="ENGLAND" YEAR="2006"/>
  <NAMEFILE FILENAME="ENG2007.csv" COUNTRY="ENGLAND" YEAR="2007"/>
  <NAMEFILE FILENAME="ENG2008.csv" COUNTRY="ENGLAND" YEAR="2008"/>
  <NAMEFILE FILENAME="ENG2009.csv" COUNTRY="ENGLAND" YEAR="2009"/>
  <NAMEFILE FILENAME="ENG2010.csv" COUNTRY="ENGLAND" YEAR="2010"/>
  <NAMEFILE FILENAME="ENG2011.csv" COUNTRY="ENGLAND" YEAR="2011"/>
  <NAMEFILE FILENAME="ENG2012.csv" COUNTRY="ENGLAND" YEAR="2012"/>
  <NAMEFILE FILENAME="ENG2013.csv" COUNTRY="ENGLAND" YEAR="2013"/>
  <NAMEFILE FILENAME="ENG2014.csv" COUNTRY="ENGLAND" YEAR="2014"/>
  <NAMEFILE FILENAME="ENG2015.csv" COUNTRY="ENGLAND" YEAR="2015"/>
  <NAMEFILE FILENAME="ENG2016.csv" COUNTRY="ENGLAND" YEAR="2016"/>
  <NAMEFILE FILENAME="ENG2017.csv" COUNTRY="ENGLAND" YEAR="2017"/>
  <NAMEFILE FILENAME="ENG2018.csv" COUNTRY="ENGLAND" YEAR="2018"/>
  <NAMEFILE FILENAME="IRL1964.csv" COUNTRY="IRELAND" YEAR="1964"/>
  <NAMEFILE FILENAME="IRL1965.csv" COUNTRY="IRELAND" YEAR="1965"/>
  <NAMEFILE FILENAME="IRL1966.csv" COUNTRY="IRELAND" YEAR="1966"/>
  <NAMEFILE FILENAME="IRL1967.csv" COUNTRY="IRELAND" YEAR="1967"/>
  <NAMEFILE FILENAME="IRL1968.csv" COUNTRY="IRELAND" YEAR="1968"/>
  <NAMEFILE FILENAME="IRL1969.csv" COUNTRY="IRELAND" YEAR="1969"/>
  <NAMEFILE FILENAME="IRL1970.csv" COUNTRY="IRELAND" YEAR="1970"/>
  <NAMEFILE FILENAME="IRL1971.csv" COUNTRY="IRELAND" YEAR="1971"/>
  <NAMEFILE FILENAME="IRL1972.csv" COUNTRY="IRELAND" YEAR="1972"/>
  <NAMEFILE FILENAME="IRL1973.csv" COUNTRY="IRELAND" YEAR="1973"/>
  <NAMEFILE FILENAME="IRL1974.csv" COUNTRY="IRELAND" YEAR="1974"/>
  <NAMEFILE FILENAME="IRL1975.csv" COUNTRY="IRELAND" YEAR="1975"/>
  <NAMEFILE FILENAME="IRL1976.csv" COUNTRY="IRELAND" YEAR="1976"/>
  <NAMEFILE FILENAME="IRL1977.csv" COUNTRY="IRELAND" YEAR="1977"/>
  <NAMEFILE FILENAME="IRL1978.csv" COUNTRY="IRELAND" YEAR="1978"/>
  <NAMEFILE FILENAME="IRL1979.csv" COUNTRY="IRELAND" YEAR="1979"/>
  <NAMEFILE FILENAME="IRL1980.csv" COUNTRY="IRELAND" YEAR="1980"/>
  <NAMEFILE FILENAME="IRL1981.csv" COUNTRY="IRELAND" YEAR="1981"/>
  <NAMEFILE FILENAME="IRL1982.csv" COUNTRY="IRELAND" YEAR="1982"/>
  <NAMEFILE FILENAME="IRL1983.csv" COUNTRY="IRELAND" YEAR="1983"/>
  <NAMEFILE FILENAME="IRL1984.csv" COUNTRY="IRELAND" YEAR="1984"/>
  <NAMEFILE FILENAME="IRL1985.csv" COUNTRY="IRELAND" YEAR="1985"/>
  <NAMEFILE FILENAME="IRL1986.csv" COUNTRY="IRELAND" YEAR="1986"/>
  <NAMEFILE FILENAME="IRL1987.csv" COUNTRY="IRELAND" YEAR="1987"/>
  <NAMEFILE FILENAME="IRL1988.csv" COUNTRY="IRELAND" YEAR="1988"/>
  <NAMEFILE FILENAME="IRL1989.csv" COUNTRY="IRELAND" YEAR="1989"/>
  <NAMEFILE FILENAME="IRL1990.csv" COUNTRY="IRELAND" YEAR="1990"/>
  <NAMEFILE FILENAME="IRL1991.csv" COUNTRY="IRELAND" YEAR="1991"/>
  <NAMEFILE FILENAME="IRL1992.csv" COUNTRY="IRELAND" YEAR="1992"/>
  <NAMEFILE FILENAME="IRL1993.csv" COUNTRY="IRELAND" YEAR="1993"/>
  <NAMEFILE FILENAME="IRL1994.csv" COUNTRY="IRELAND" YEAR="1994"/>
  <NAMEFILE FILENAME="IRL1995.csv" COUNTRY="IRELAND" YEAR="1995"/>
  <NAMEFILE FILENAME="IRL1996.csv" COUNTRY="IRELAND" YEAR="1996"/>
  <NAMEFILE FILENAME="IRL1997.csv" COUNTRY="IRELAND" YEAR="1997"/>
  <NAMEFILE FILENAME="IRL1998.csv" COUNTRY="IRELAND" YEAR="1998"/>
  <NAMEFILE FILENAME="IRL1999.csv" COUNTRY="IRELAND" YEAR="1999"/>
  <NAMEFILE FILENAME="IRL2000.csv" COUNTRY="IRELAND" YEAR="2000"/>
  <NAMEFILE FILENAME="IRL2001.csv" COUNTRY="IRELAND" YEAR="2001"/>
  <NAMEFILE FILENAME="IRL2002.csv" COUNTRY="IRELAND" YEAR="2002"/>
  <NAMEFILE FILENAME="IRL2003.csv" COUNTRY="IRELAND" YEAR="2003"/>
  <NAMEFILE FILENAME="IRL2004.csv" COUNTRY="IRELAND" YEAR="2004"/>
  <NAMEFILE FILENAME="IRL2005.csv" COUNTRY="IRELAND" YEAR="2005"/>
  <NAMEFILE FILENAME="IRL2006.csv" COUNTRY="IRELAND" YEAR="2006"/>
  <NAMEFILE FILENAME="IRL2007.csv" COUNTRY="IRELAND" YEAR="2007"/>
  <NAMEFILE FILENAME="IRL2008.csv" COUNTRY="IRELAND" YEAR="2008"/>
  <NAMEFILE FILENAME="IRL2009.csv" COUNTRY="IRELAND" YEAR="2009"/>
  <NAMEFILE FILENAME="IRL2010.csv" COUNTRY="IRELAND" YEAR="2010"/>
  <NAMEFILE FILENAME="IRL2011.csv" COUNTRY="IRELAND" YEAR="2011"/>
  <NAMEFILE FILENAME="IRL2012.csv" COUNTRY="IRELAND" YEAR="2012"/>
  <NAMEFILE FILENAME="IRL2013.csv" COUNTRY="IRELAND" YEAR="2013"/>
  <NAMEFILE FILENAME="IRL2014.csv" COUNTRY="IRELAND" YEAR="2014"/>
  <NAMEFILE FILENAME="IRL2015.csv" COUNTRY="IRELAND" YEAR="2015"/>
  <NAMEFILE FILENAME="IRL2016.csv" COUNTRY="IRELAND" YEAR="2016"/>
  <NAMEFILE FILENAME="IRL2017.csv" COUNTRY="IRELAND" YEAR="2017"/>
  <NAMEFILE FILENAME="IRL2018.csv" COUNTRY="IRELAND" YEAR="2018"/>
  <NAMEFILE FILENAME="NIR1997.csv" COUNTRY="NORTHERN IRELAND" YEAR="1997"/>
  <NAMEFILE FILENAME="NIR1998.csv" COUNTRY="NORTHERN IRELAND" YEAR="1998"/>
  <NAMEFILE FILENAME="NIR1999.csv" COUNTRY="NORTHERN IRELAND" YEAR="1999"/>
  <NAMEFILE FILENAME="NIR2000.csv" COUNTRY="NORTHERN IRELAND" YEAR="2000"/>
  <NAMEFILE FILENAME="NIR2001.csv" COUNTRY="NORTHERN IRELAND" YEAR="2001"/>
  <NAMEFILE FILENAME="NIR2002.csv" COUNTRY="NORTHERN IRELAND" YEAR="2002"/>
  <NAMEFILE FILENAME="NIR2003.csv" COUNTRY="NORTHERN IRELAND" YEAR="2003"/>
  <NAMEFILE FILENAME="NIR2004.csv" COUNTRY="NORTHERN IRELAND" YEAR="2004"/>
  <NAMEFILE FILENAME="NIR2005.csv" COUNTRY="NORTHERN IRELAND" YEAR="2005"/>
  <NAMEFILE FILENAME="NIR2006.csv" COUNTRY="NORTHERN IRELAND" YEAR="2006"/>
  <NAMEFILE FILENAME="NIR2007.csv" COUNTRY="NORTHERN IRELAND" YEAR="2007"/>
  <NAMEFILE FILENAME="NIR2008.csv" COUNTRY="NORTHERN IRELAND" YEAR="2008"/>
  <NAMEFILE FILENAME="NIR2009.csv" COUNTRY="NORTHERN IRELAND" YEAR="2009"/>
  <NAMEFILE FILENAME="NIR2010.csv" COUNTRY="NORTHERN IRELAND" YEAR="2010"/>
  <NAMEFILE FILENAME="NIR2011.csv" COUNTRY="NORTHERN IRELAND" YEAR="2011"/>
  <NAMEFILE FILENAME="NIR2012.csv" COUNTRY="NORTHERN IRELAND" YEAR="2012"/>
  <NAMEFILE FILENAME="NIR2013.csv" COUNTRY="NORTHERN IRELAND" YEAR="2013"/>
  <NAMEFILE FILENAME="NIR2014.csv" COUNTRY="NORTHERN IRELAND" YEAR="2014"/>
  <NAMEFILE FILENAME="NIR2015.csv" COUNTRY="NORTHERN IRELAND" YEAR="2015"/>
  <NAMEFILE FILENAME="NIR2016.csv" COUNTRY="NORTHERN IRELAND" YEAR="2016"/>
  <NAMEFILE FILENAME="NIR2017.csv" COUNTRY="NORTHERN IRELAND" YEAR="2017"/>
  <NAMEFILE FILENAME="NIR2018.csv" COUNTRY="NORTHERN IRELAND" YEAR="2018"/>
  <NAMEFILE FILENAME="SCT1974.csv" COUNTRY="SCOTLAND" YEAR="1974"/>
  <NAMEFILE FILENAME="SCT1975.csv" COUNTRY="SCOTLAND" YEAR="1975"/>
  <NAMEFILE FILENAME="SCT1976.csv" COUNTRY="SCOTLAND" YEAR="1976"/>
  <NAMEFILE FILENAME="SCT1977.csv" COUNTRY="SCOTLAND" YEAR="1977"/>
  <NAMEFILE FILENAME="SCT1978.csv" COUNTRY="SCOTLAND" YEAR="1978"/>
  <NAMEFILE FILENAME="SCT1979.csv" COUNTRY="SCOTLAND" YEAR="1979"/>
  <NAMEFILE FILENAME="SCT1980.csv" COUNTRY="SCOTLAND" YEAR="1980"/>
  <NAMEFILE FILENAME="SCT1981.csv" COUNTRY="SCOTLAND" YEAR="1981"/>
  <NAMEFILE FILENAME="SCT1982.csv" COUNTRY="SCOTLAND" YEAR="1982"/>
  <NAMEFILE FILENAME="SCT1983.csv" COUNTRY="SCOTLAND" YEAR="1983"/>
  <NAMEFILE FILENAME="SCT1984.csv" COUNTRY="SCOTLAND" YEAR="1984"/>
  <NAMEFILE FILENAME="SCT1985.csv" COUNTRY="SCOTLAND" YEAR="1985"/>
  <NAMEFILE FILENAME="SCT1986.csv" COUNTRY="SCOTLAND" YEAR="1986"/>
  <NAMEFILE FILENAME="SCT1987.csv" COUNTRY="SCOTLAND" YEAR="1987"/>
  <NAMEFILE FILENAME="SCT1988.csv" COUNTRY="SCOTLAND" YEAR="1988"/>
  <NAMEFILE FILENAME="SCT1989.csv" COUNTRY="SCOTLAND" YEAR="1989"/>
  <NAMEFILE FILENAME="SCT1990.csv" COUNTRY="SCOTLAND" YEAR="1990"/>
  <NAMEFILE FILENAME="SCT1991.csv" COUNTRY="SCOTLAND" YEAR="1991"/>
  <NAMEFILE FILENAME="SCT1992.csv" COUNTRY="SCOTLAND" YEAR="1992"/>
  <NAMEFILE FILENAME="SCT1993.csv" COUNTRY="SCOTLAND" YEAR="1993"/>
  <NAMEFILE FILENAME="SCT1994.csv" COUNTRY="SCOTLAND" YEAR="1994"/>
  <NAMEFILE FILENAME="SCT1995.csv" COUNTRY="SCOTLAND" YEAR="1995"/>
  <NAMEFILE FILENAME="SCT1996.csv" COUNTRY="SCOTLAND" YEAR="1996"/>
  <NAMEFILE FILENAME="SCT1997.csv" COUNTRY="SCOTLAND" YEAR="1997"/>
  <NAMEFILE FILENAME="SCT1998.csv" COUNTRY="SCOTLAND" YEAR="1998"/>
  <NAMEFILE FILENAME="SCT1999.csv" COUNTRY="SCOTLAND" YEAR="1999"/>
  <NAMEFILE FILENAME="SCT2000.csv" COUNTRY="SCOTLAND" YEAR="2000"/>
  <NAMEFILE FILENAME="SCT2001.csv" COUNTRY="SCOTLAND" YEAR="2001"/>
  <NAMEFILE FILENAME="SCT2002.csv" COUNTRY="SCOTLAND" YEAR="2002"/>
  <NAMEFILE FILENAME="SCT2003.csv" COUNTRY="SCOTLAND" YEAR="2003"/>
  <NAMEFILE FILENAME="SCT2004.csv" COUNTRY="SCOTLAND" YEAR="2004"/>
  <NAMEFILE FILENAME="SCT2005.csv" COUNTRY="SCOTLAND" YEAR="2005"/>
  <NAMEFILE FILENAME="SCT2006.csv" COUNTRY="SCOTLAND" YEAR="2006"/>
  <NAMEFILE FILENAME="SCT2007.csv" COUNTRY="SCOTLAND" YEAR="2007"/>
  <NAMEFILE FILENAME="SCT2008.csv" COUNTRY="SCOTLAND" YEAR="2008"/>
  <NAMEFILE FILENAME="SCT2009.csv" COUNTRY="SCOTLAND" YEAR="2009"/>
  <NAMEFILE FILENAME="SCT2010.csv" COUNTRY="SCOTLAND" YEAR="2010"/>
  <NAMEFILE FILENAME="SCT2011.csv" COUNTRY="SCOTLAND" YEAR="2011"/>
  <NAMEFILE FILENAME="SCT2012.csv" COUNTRY="SCOTLAND" YEAR="2012"/>
  <NAMEFILE FILENAME="SCT2013.csv" COUNTRY="SCOTLAND" YEAR="2013"/>
  <NAMEFILE FILENAME="SCT2014.csv" COUNTRY="SCOTLAND" YEAR="2014"/>
  <NAMEFILE FILENAME="SCT2015.csv" COUNTRY="SCOTLAND" YEAR="2015"/>
  <NAMEFILE FILENAME="SCT2016.csv" COUNTRY="SCOTLAND" YEAR="2016"/>
  <NAMEFILE FILENAME="SCT2017.csv" COUNTRY="SCOTLAND" YEAR="2017"/>
  <NAMEFILE FILENAME="SCT2018.csv" COUNTRY="SCOTLAND" YEAR="2018"/>
  <NAMEFILE FILENAME="USA1930.csv" COUNTRY="UNITED STATES" YEAR="1930"/>
  <NAMEFILE FILENAME="USA1931.csv" COUNTRY="UNITED STATES" YEAR="1931"/>
  <NAMEFILE FILENAME="USA1932.csv" COUNTRY="UNITED STATES" YEAR="1932"/>
  <NAMEFILE FILENAME="USA1933.csv" COUNTRY="UNITED STATES" YEAR="1933"/>
  <NAMEFILE FILENAME="USA1934.csv" COUNTRY="UNITED STATES" YEAR="1934"/>
  <NAMEFILE FILENAME="USA1935.csv" COUNTRY="UNITED STATES" YEAR="1935"/>
  <NAMEFILE FILENAME="USA1936.csv" COUNTRY="UNITED STATES" YEAR="1936"/>
  <NAMEFILE FILENAME="USA1937.csv" COUNTRY="UNITED STATES" YEAR="1937"/>
  <NAMEFILE FILENAME="USA1938.csv" COUNTRY="UNITED STATES" YEAR="1938"/>
  <NAMEFILE FILENAME="USA1939.csv" COUNTRY="UNITED STATES" YEAR="1939"/>
  <NAMEFILE FILENAME="USA1940.csv" COUNTRY="UNITED STATES" YEAR="1940"/>
  <NAMEFILE FILENAME="USA1941.csv" COUNTRY="UNITED STATES" YEAR="1941"/>
  <NAMEFILE FILENAME="USA1942.csv" COUNTRY="UNITED STATES" YEAR="1942"/>
  <NAMEFILE FILENAME="USA1943.csv" COUNTRY="UNITED STATES" YEAR="1943"/>
  <NAMEFILE FILENAME="USA1944.csv" COUNTRY="UNITED STATES" YEAR="1944"/>
  <NAMEFILE FILENAME="USA1945.csv" COUNTRY="UNITED STATES" YEAR="1945"/>
  <NAMEFILE FILENAME="USA1946.csv" COUNTRY="UNITED STATES" YEAR="1946"/>
  <NAMEFILE FILENAME="USA1947.csv" COUNTRY="UNITED STATES" YEAR="1947"/>
  <NAMEFILE FILENAME="USA1948.csv" COUNTRY="UNITED STATES" YEAR="1948"/>
  <NAMEFILE FILENAME="USA1949.csv" COUNTRY="UNITED STATES" YEAR="1949"/>
  <NAMEFILE FILENAME="USA1950.csv" COUNTRY="UNITED STATES" YEAR="1950"/>
  <NAMEFILE FILENAME="USA1951.csv" COUNTRY="UNITED STATES" YEAR="1951"/>
  <NAMEFILE FILENAME="USA1952.csv" COUNTRY="UNITED STATES" YEAR="1952"/>
  <NAMEFILE FILENAME="USA1953.csv" COUNTRY="UNITED STATES" YEAR="1953"/>
  <NAMEFILE FILENAME="USA1954.csv" COUNTRY="UNITED STATES" YEAR="1954"/>
  <NAMEFILE FILENAME="USA1955.csv" COUNTRY="UNITED STATES" YEAR="1955"/>
  <NAMEFILE FILENAME="USA1956.csv" COUNTRY="UNITED STATES" YEAR="1956"/>
  <NAMEFILE FILENAME="USA1957.csv" COUNTRY="UNITED STATES" YEAR="1957"/>
  <NAMEFILE FILENAME="USA1958.csv" COUNTRY="UNITED STATES" YEAR="1958"/>
  <NAMEFILE FILENAME="USA1959.csv" COUNTRY="UNITED STATES" YEAR="1959"/>
  <NAMEFILE FILENAME="USA1960.csv" COUNTRY="UNITED STATES" YEAR="1960"/>
  <NAMEFILE FILENAME="USA1961.csv" COUNTRY="UNITED STATES" YEAR="1961"/>
  <NAMEFILE FILENAME="USA1962.csv" COUNTRY="UNITED STATES" YEAR="1962"/>
  <NAMEFILE FILENAME="USA1963.csv" COUNTRY="UNITED STATES" YEAR="1963"/>
  <NAMEFILE FILENAME="USA1964.csv" COUNTRY="UNITED STATES" YEAR="1964"/>
  <NAMEFILE FILENAME="USA1965.csv" COUNTRY="UNITED STATES" YEAR="1965"/>
  <NAMEFILE FILENAME="USA1966.csv" COUNTRY="UNITED STATES" YEAR="1966"/>
  <NAMEFILE FILENAME="USA1967.csv" COUNTRY="UNITED STATES" YEAR="1967"/>
  <NAMEFILE FILENAME="USA1968.csv" COUNTRY="UNITED STATES" YEAR="1968"/>
  <NAMEFILE FILENAME="USA1969.csv" COUNTRY="UNITED STATES" YEAR="1969"/>
  <NAMEFILE FILENAME="USA1970.csv" COUNTRY="UNITED STATES" YEAR="1970"/>
  <NAMEFILE FILENAME="USA1971.csv" COUNTRY="UNITED STATES" YEAR="1971"/>
  <NAMEFILE FILENAME="USA1972.csv" COUNTRY="UNITED STATES" YEAR="1972"/>
  <NAMEFILE FILENAME="USA1973.csv" COUNTRY="UNITED STATES" YEAR="1973"/>
  <NAMEFILE FILENAME="USA1974.csv" COUNTRY="UNITED STATES" YEAR="1974"/>
  <NAMEFILE FILENAME="USA1975.csv" COUNTRY="UNITED STATES" YEAR="1975"/>
  <NAMEFILE FILENAME="USA1976.csv" COUNTRY="UNITED STATES" YEAR="1976"/>
  <NAMEFILE FILENAME="USA1977.csv" COUNTRY="UNITED STATES" YEAR="1977"/>
  <NAMEFILE FILENAME="USA1978.csv" COUNTRY="UNITED STATES" YEAR="1978"/>
  <NAMEFILE FILENAME="USA1979.csv" COUNTRY="UNITED STATES" YEAR="1979"/>
  <NAMEFILE FILENAME="USA1980.csv" COUNTRY="UNITED STATES" YEAR="1980"/>
  <NAMEFILE FILENAME="USA1981.csv" COUNTRY="UNITED STATES" YEAR="1981"/>
  <NAMEFILE FILENAME="USA1982.csv" COUNTRY="UNITED STATES" YEAR="1982"/>
  <NAMEFILE FILENAME="USA1983.csv" COUNTRY="UNITED STATES" YEAR="1983"/>
  <NAMEFILE FILENAME="USA1984.csv" COUNTRY="UNITED STATES" YEAR="1984"/>
  <NAMEFILE FILENAME="USA1985.csv" COUNTRY="UNITED STATES" YEAR="1985"/>
  <NAMEFILE FILENAME="USA1986.csv" COUNTRY="UNITED STATES" YEAR="1986"/>
  <NAMEFILE FILENAME="USA1987.csv" COUNTRY="UNITED STATES" YEAR="1987"/>
  <NAMEFILE FILENAME="USA1988.csv" COUNTRY="UNITED STATES" YEAR="1988"/>
  <NAMEFILE FILENAME="USA1989.csv" COUNTRY="UNITED STATES" YEAR="1989"/>
  <NAMEFILE FILENAME="USA1990.csv" COUNTRY="UNITED STATES" YEAR="1990"/>
  <NAMEFILE FILENAME="USA1991.csv" COUNTRY="UNITED STATES" YEAR="1991"/>
  <NAMEFILE FILENAME="USA1992.csv" COUNTRY="UNITED STATES" YEAR="1992"/>
  <NAMEFILE FILENAME="USA1993.csv" COUNTRY="UNITED STATES" YEAR="1993"/>
  <NAMEFILE FILENAME="USA1994.csv" COUNTRY="UNITED STATES" YEAR="1994"/>
  <NAMEFILE FILENAME="USA1995.csv" COUNTRY="UNITED STATES" YEAR="1995"/>
  <NAMEFILE FILENAME="USA1996.csv" COUNTRY="UNITED STATES" YEAR="1996"/>
  <NAMEFILE FILENAME="USA1997.csv" COUNTRY="UNITED STATES" YEAR="1997"/>
  <NAMEFILE FILENAME="USA1998.csv" COUNTRY="UNITED STATES" YEAR="1998"/>
  <NAMEFILE FILENAME="USA1999.csv" COUNTRY="UNITED STATES" YEAR="1999"/>
  <NAMEFILE FILENAME="USA2000.csv" COUNTRY="UNITED STATES" YEAR="2000"/>
  <NAMEFILE FILENAME="USA2001.csv" COUNTRY="UNITED STATES" YEAR="2001"/>
  <NAMEFILE FILENAME="USA2002.csv" COUNTRY="UNITED STATES" YEAR="2002"/>
  <NAMEFILE FILENAME="USA2003.csv" COUNTRY="UNITED STATES" YEAR="2003"/>
  <NAMEFILE FILENAME="USA2004.csv" COUNTRY="UNITED STATES" YEAR="2004"/>
  <NAMEFILE FILENAME="USA2005.csv" COUNTRY="UNITED STATES" YEAR="2005"/>
  <NAMEFILE FILENAME="USA2006.csv" COUNTRY="UNITED STATES" YEAR="2006"/>
  <NAMEFILE FILENAME="USA2007.csv" COUNTRY="UNITED STATES" YEAR="2007"/>
  <NAMEFILE FILENAME="USA2008.csv" COUNTRY="UNITED STATES" YEAR="2008"/>
  <NAMEFILE FILENAME="USA2009.csv" COUNTRY="UNITED STATES" YEAR="2009"/>
  <NAMEFILE FILENAME="USA2010.csv" COUNTRY="UNITED STATES" YEAR="2010"/>
  <NAMEFILE FILENAME="USA2011.csv" COUNTRY="UNITED STATES" YEAR="2011"/>
  <NAMEFILE FILENAME="USA2012.csv" COUNTRY="UNITED STATES" YEAR="2012"/>
  <NAMEFILE FILENAME="USA2013.csv" COUNTRY="UNITED STATES" YEAR="2013"/>
  <NAMEFILE FILENAME="USA2014.csv" COUNTRY="UNITED STATES" YEAR="2014"/>
  <NAMEFILE FILENAME="USA2015.csv" COUNTRY="UNITED STATES" YEAR="2015"/>
  <NAMEFILE FILENAME="USA2016.csv" COUNTRY="UNITED STATES" YEAR="2016"/>
  <NAMEFILE FILENAME="USA2017.csv" COUNTRY="UNITED STATES" YEAR="2017"/>
  <NAMEFILE FILENAME="USA2018.csv" COUNTRY="UNITED STATES" YEAR="2018"/>
</NAMEFILES>
